SEAS/__init__.py
SEAS/Assets/__init__.py
SEAS/Engine/__init__.py
SEAS/Engine/Components/__init__.py
SEAS/Engine/Components/characterPolyControllerComp.py
SEAS/Engine/Components/collidePolyComp.py
SEAS/Engine/Components/gravityComp.py
SEAS/Engine/Components/hitboxPolyComp.py
SEAS/Engine/Components/renderPolyComp.py
SEAS/Engine/Components/renderRectComp.py
SEAS/Engine/Components/transformPolyComp.py
SEAS/Engine/Components/transformRectComp.py
SEAS/Engine/Core/__init__.py
SEAS/Engine/Core/core.py
SEAS/Engine/Core/coreModule.py
SEAS/Engine/Core/event.py
SEAS/Engine/Core/filePreset.py
SEAS/Engine/Core/font.py
SEAS/Engine/Core/input.py
SEAS/Engine/Core/screen.py
SEAS/Engine/Game/__init__.py
SEAS/Engine/Game/run.py
SEAS/Engine/Maths/__init__.py
SEAS/Engine/Maths/maths.py
SEAS/Engine/Models/__init__.py
SEAS/Engine/Models/emptyModel.py
SEAS/Engine/Scene/__init__.py
SEAS/Engine/Scene/scene.py
SEAS/Engine/Setup/__init__.py
SEAS/Engine/Setup/pygameSetup.py
SEAS/UI/__init__.py
MySEAS_OLD-1.0.11.dist-info/METADATA
MySEAS_OLD-1.0.11.dist-info/WHEEL
MySEAS_OLD-1.0.11.dist-info/top_level.txt
MySEAS_OLD-1.0.11.dist-info/RECORD
