Metadata-Version: 2.1
Name: MySEAS-OLD
Version: 1.0.11
Summary: A Simple Game Engine Libary
Author: Sixten Bohman
Author-email: sixten.bohman.08@gmail.com
Keywords: python,pygame,Game Engine,Simple,Beginner,Learning,Funny?
Classifier: Development Status :: 1 - Planning
Classifier: Intended Audience :: Developers
Classifier: Programming Language :: Python :: 3
Classifier: Operating System :: Unix
Classifier: Operating System :: MacOS :: MacOS X
Classifier: Operating System :: Microsoft :: Windows
Requires-Dist: pygame
